LICENSE
README.md
setup.py
pyoscvideo/__init__.py
pyoscvideo/__main__.py
pyoscvideo/vlc_record_webcam.py
pyoscvideo.egg-info/PKG-INFO
pyoscvideo.egg-info/SOURCES.txt
pyoscvideo.egg-info/dependency_links.txt
pyoscvideo.egg-info/entry_points.txt
pyoscvideo.egg-info/requires.txt
pyoscvideo.egg-info/top_level.txt
pyoscvideo/gui/camera_view.py
pyoscvideo/gui/camera_view_ui.py
pyoscvideo/gui/fixed_aspect_label.py
pyoscvideo/gui/main_view.py
pyoscvideo/gui/main_view_ui.py
pyoscvideo/helpers/helpers.py
pyoscvideo/helpers/settings.py
pyoscvideo/helpers/v4l2.py
pyoscvideo/logging/logging_settings.json
pyoscvideo/osc/interface.py
pyoscvideo/player/__main__.py
pyoscvideo/video/camera.py
pyoscvideo/video/camera_reader.py
pyoscvideo/video/camera_selector.py
pyoscvideo/video/manager.py
pyoscvideo/video/video_writer.py
pyoscvideo/video/tests/test_camera.py