Metadata-Version: 2.1
Name: pyoscvideo
Version: 0.2.0
Summary: Synchronized multi-video recorder and player, controllable via OSC
Home-page: https://github.com/Sentire-Dev/pyOscVideo
Author: Sentire
Author-email: hello@sentire.me
License: UNKNOWN
Keywords: osc video player recorder webcam
Platform: UNKNOWN
Classifier: Programming Language :: Python :: 3
Classifier: License :: OSI Approved :: GNU General Public License v3 or later (GPLv3+)
Classifier: Operating System :: MacOS
Classifier: Operating System :: POSIX :: Linux
Classifier: Topic :: Multimedia :: Video :: Capture
Classifier: Topic :: Multimedia :: Video :: Display
Requires-Python: >3.7
License-File: LICENSE
